mcp_server_oracle/__init__.py
mcp_server_oracle/oracle_tools.py
oracle_db_mcp-0.0.1.dist-info/METADATA
oracle_db_mcp-0.0.1.dist-info/WHEEL
oracle_db_mcp-0.0.1.dist-info/entry_points.txt
oracle_db_mcp-0.0.1.dist-info/licenses/LICENSE
oracle_db_mcp-0.0.1.dist-info/RECORD
